<xml xmlns="http://www.w3.org/1999/xhtml" collection="false">
  <variables>
    <variable type="" id="[ALbnKAase=Els_`)hUl">Sp</variable>
    <variable type="" id="G(73Nc#jgMZ$1;5OU8My">Initial Amount</variable>
    <variable type="" id="#dZi9;2T@X-Nx|piac!l">promedio_ticks</variable>
    <variable type="" id="(5l7?QBe%F}9JdwBk^!e">ekse</variable>
    <variable type="" id="7([F3U3H^l{pMDX9r(WZ">Jloss</variable>
    <variable type="" id="=1$vClxY+2pTTnp]@oAR">Quiero Ganar:</variable>
    <variable type="" id="imK2x@=6Mc1~)fsfBWx-">::: Umbral de referencia</variable>
    <variable type="" id="i:Z4!f)D|*s,oET(5.yJ">logika</variable>
    <variable type="" id="a;P]ajpvJ|Wzma0#|Kzd">Estoy dispuesto a perder:</variable>
    <variable type="" id="Y?yw~SXhjd}Hc/9{;jW4">ema</variable>
    <variable type="" id="+1/Ux:bV9I$!t23w54JE">La inversión será:</variable>
    <variable type="" id="pwK]FTksg[*.9=~*$|5H">ma</variable>
    <variable type="" id="o/=0QCkDSD0FNOZ4LUcH">posisi</variable>
    <variable type="" id="-4oe3o=zU$tKk^Iqkyjo">Inversión inicial</variable>
    <variable type="" id="6?!)Gp;c:,Q@tcC$OIak">Inversion</variable>
    <variable type="" id="ZuswH/nz_@gI!C[YU)%j">i</variable>
  </variables>
  <block type="trade" id="trade" x="0" y="0">
    <field name="MARKET_LIST">synthetic_index</field>
    <field name="SUBMARKET_LIST">random_index</field>
    <field name="SYMBOL_LIST">R_100</field>
    <field name="TRADETYPECAT_LIST">callput</field>
    <field name="TRADETYPE_LIST">risefall</field>
    <field name="TYPE_LIST">both</field>
    <field name="CANDLEINTERVAL_LIST">60</field>
    <field name="TIME_MACHINE_ENABLED">FALSE</field>
    <field name="RESTARTONERROR">TRUE</field>
    <statement name="INITIALIZATION">
      <block type="notify" id="Jpg-F1aB|F~eVXX_.5S!" collapsed="true">
        <field name="NOTIFICATION_TYPE">success</field>
        <field name="NOTIFICATION_SOUND">silent</field>
        <value name="MESSAGE">
          <shadow type="text" id="yGEVn)6{{iuO::PyFmcL">
            <field name="TEXT">  🤖     BOTGRATIS12    🤖</field>
          </shadow>
        </value>
        <next>
          <block type="notify" id="RINIKt1nx)St9K=UraSS" collapsed="true">
            <field name="NOTIFICATION_TYPE">info</field>
            <field name="NOTIFICATION_SOUND">silent</field>
            <value name="MESSAGE">
              <shadow type="text" id="Ns0Vt:n!OxqFBR}B4+Tl">
                <field name="TEXT">  🤖     SWIFT    🤖</field>
              </shadow>
            </value>
            <next>
              <block type="variables_set" id="Ya;]I6BNmfjJRe;:{/:H">
                <field name="VAR" id="=1$vClxY+2pTTnp]@oAR" variabletype="">Quiero Ganar:</field>
                <value name="VALUE">
                  <block type="math_number" id="R(g2y0eoK;zK8]IK(p)g">
                    <field name="NUM">2000</field>
                  </block>
                </value>
                <next>
                  <block type="variables_set" id="DK9UX{gG^NYmc.twyXZZ">
                    <field name="VAR" id="a;P]ajpvJ|Wzma0#|Kzd" variabletype="">Estoy dispuesto a perder:</field>
                    <value name="VALUE">
                      <block type="math_number" id=":-6SU024*3^jAd9VJ*wt">
                        <field name="NUM">50</field>
                      </block>
                    </value>
                    <next>
                      <block type="variables_set" id="C1au^uTT5wpy{A(#/n|7">
                        <field name="VAR" id="+1/Ux:bV9I$!t23w54JE" variabletype="">La inversión será:</field>
                        <value name="VALUE">
                          <block type="math_number" id="HZmz-z]%bnfz.WD3Gi!;">
                            <field name="NUM">0.35</field>
                          </block>
                        </value>
                        <next>
                          <block type="variables_set" id="Zk}:J;|}4w,2xx6s=(s/">
                            <field name="VAR" id="G(73Nc#jgMZ$1;5OU8My" variabletype="">Initial Amount</field>
                            <value name="VALUE">
                              <block type="variables_get" id="8qy!.pO@Z)HPzMo3tcv7">
                                <field name="VAR" id="+1/Ux:bV9I$!t23w54JE" variabletype="">La inversión será:</field>
                              </block>
                            </value>
                            <next>
                              <block type="variables_set" id="[zH!MlEo9+qQ@nAZ@T,5" collapsed="true">
                                <field name="VAR" id="[ALbnKAase=Els_`)hUl" variabletype="">Sp</field>
                                <value name="VALUE">
                                  <block type="math_number" id="@a.$,ani|i/XIxzQ:7X%">
                                    <field name="NUM">15</field>
                                  </block>
                                </value>
                                <next>
                                  <block type="variables_set" id="M49VPQ*-0LP*e0)AU}gu" collapsed="true">
                                    <field name="VAR" id="(5l7?QBe%F}9JdwBk^!e" variabletype="">ekse</field>
                                    <value name="VALUE">
                                      <block type="math_number" id="M.1V~##U~GBQT~C^ETc4">
                                        <field name="NUM">0</field>
                                      </block>
                                    </value>
                                    <next>
                                      <block type="variables_set" id="R%$FTiZmXcTqLT{]@~*[" collapsed="true">
                                        <field name="VAR" id="i:Z4!f)D|*s,oET(5.yJ" variabletype="">logika</field>
                                        <value name="VALUE">
                                          <block type="math_number" id="wFolFQBH%zEUS!Jn@rOq">
                                            <field name="NUM">1</field>
                                          </block>
                                        </value>
                                        <next>
                                          <block type="variables_set" id="gx=`LFtqy/Y2TroQcM[M" collapsed="true">
                                            <field name="VAR" id="7([F3U3H^l{pMDX9r(WZ" variabletype="">Jloss</field>
                                            <value name="VALUE">
                                              <block type="math_number" id="Sd[GFV),874ATM/Xq3%P">
                                                <field name="NUM">0</field>
                                              </block>
                                            </value>
                                            <next>
                                              <block type="variables_set" id="77=Px|U%Uw1wgrz~?d2j" collapsed="true">
                                                <field name="VAR" id="-4oe3o=zU$tKk^Iqkyjo" variabletype="">Inversión inicial</field>
                                                <value name="VALUE">
                                                  <block type="variables_get" id=";LL2bP{yrgeABL_n.lPO" collapsed="true">
                                                    <field name="VAR" id="6?!)Gp;c:,Q@tcC$OIak" variabletype="">Inversion</field>
                                                  </block>
                                                </value>
                                                <next>
                                                  <block type="variables_set" id="fOj+Qj=Th+yZ_/Lk0|b{" collapsed="true">
                                                    <field name="VAR" id="#dZi9;2T@X-Nx|piac!l" variabletype="">promedio_ticks</field>
                                                    <value name="VALUE">
                                                      <block type="lists_create_with" id="9PfqFYl:bS3m4ncrf:+;">
                                                        <mutation items="0"></mutation>
                                                      </block>
                                                    </value>
                                                    <next>
                                                      <block type="controls_for" id="Otm%a)1-rj5dO?f#a_+c" collapsed="true">
                                                        <field name="VAR" id="ZuswH/nz_@gI!C[YU)%j" variabletype="">i</field>
                                                        <value name="FROM">
                                                          <block type="math_number" id="Vk:E{VZ66$!b;LBk_n%=">
                                                            <field name="NUM">60</field>
                                                          </block>
                                                        </value>
                                                        <value name="TO">
                                                          <block type="math_number" id="^6W/;pt6`3qWpBD(gul)">
                                                            <field name="NUM">1</field>
                                                          </block>
                                                        </value>
                                                        <value name="BY">
                                                          <block type="math_number" id="QLqE[s}g61jX^:;[[4MT">
                                                            <field name="NUM">1</field>
                                                          </block>
                                                        </value>
                                                        <statement name="DO">
                                                          <block type="lists_setIndex" id=")5.tW0`XS/-;Q5]UM?_3">
                                                            <mutation at="false"></mutation>
                                                            <field name="MODE">INSERT</field>
                                                            <field name="WHERE">LAST</field>
                                                            <value name="LIST">
                                                              <block type="variables_get" id="Gb8ShaX0imhs!MsojmhX">
                                                                <field name="VAR" id="#dZi9;2T@X-Nx|piac!l" variabletype="">promedio_ticks</field>
                                                              </block>
                                                            </value>
                                                            <value name="TO">
                                                              <block type="math_single" id="XEmN[%]}Gcze7P7Bn#Je">
                                                                <field name="OP">ABS</field>
                                                                <value name="NUM">
                                                                  <shadow type="math_number" id="A{hd8uh?~owsKX:},#~E">
                                                                    <field name="NUM">9</field>
                                                                  </shadow>
                                                                  <block type="math_arithmetic" id="A`kk64x@-bn27?nAMZ^:" inline="false">
                                                                    <field name="OP">MINUS</field>
                                                                    <value name="A">
                                                                      <shadow type="math_number" id="D{r[4}i6APj~/`JU$||Z">
                                                                        <field name="NUM">1</field>
                                                                      </shadow>
                                                                      <block type="lists_getIndex" id="gS+@bM}v*_)kb}y)AYZl">
                                                                        <mutation statement="false" at="true"></mutation>
                                                                        <field name="MODE">GET</field>
                                                                        <field name="WHERE">FROM_END</field>
                                                                        <value name="VALUE">
                                                                          <block type="ticks" id="0kY=u7):x[Lk?Lz4o7;^"></block>
                                                                        </value>
                                                                        <value name="AT">
                                                                          <block type="variables_get" id="`=:8!%C/XrM*!^)4=H~:">
                                                                            <field name="VAR" id="ZuswH/nz_@gI!C[YU)%j" variabletype="">i</field>
                                                                          </block>
                                                                        </value>
                                                                      </block>
                                                                    </value>
                                                                    <value name="B">
                                                                      <shadow type="math_number" id="@eof_=)puL~P_K4X=R$,">
                                                                        <field name="NUM">1</field>
                                                                      </shadow>
                                                                      <block type="lists_getIndex" id="]ImukK[OV)};u3wbPgkP">
                                                                        <mutation statement="false" at="true"></mutation>
                                                                        <field name="MODE">GET</field>
                                                                        <field name="WHERE">FROM_END</field>
                                                                        <value name="VALUE">
                                                                          <block type="ticks" id="}TDb@amm;4,M.$!kP/hZ"></block>
                                                                        </value>
                                                                        <value name="AT">
                                                                          <block type="math_arithmetic" id="1nU6-V5a2gd)$|9A8w~k">
                                                                            <field name="OP">ADD</field>
                                                                            <value name="A">
                                                                              <shadow type="math_number" id="9O}y0$Ll(Ci1w7N`i*nc">
                                                                                <field name="NUM">1</field>
                                                                              </shadow>
                                                                              <block type="variables_get" id="kJ9ME[?(8GBp6?_oJQ.5">
                                                                                <field name="VAR" id="ZuswH/nz_@gI!C[YU)%j" variabletype="">i</field>
                                                                              </block>
                                                                            </value>
                                                                            <value name="B">
                                                                              <shadow type="math_number" id="?4WlyvpJ}cAW~eq|d!2y">
                                                                                <field name="NUM">1</field>
                                                                              </shadow>
                                                                              <block type="math_number" id="z7id/m}N($)IkPJ~Npou">
                                                                                <field name="NUM">1</field>
                                                                              </block>
                                                                            </value>
                                                                          </block>
                                                                        </value>
                                                                      </block>
                                                                    </value>
                                                                  </block>
                                                                </value>
                                                              </block>
                                                            </value>
                                                          </block>
                                                        </statement>
                                                      </block>
                                                    </next>
                                                  </block>
                                                </next>
                                              </block>
                                            </next>
                                          </block>
                                        </next>
                                      </block>
                                    </next>
                                  </block>
                                </next>
                              </block>
                            </next>
                          </block>
                        </next>
                      </block>
                    </next>
                  </block>
                </next>
              </block>
            </next>
          </block>
        </next>
      </block>
    </statement>
    <statement name="SUBMARKET">
      <block type="tradeOptions" id="AWk/hnI=R}p/f,wrPMMe">
        <field name="DURATIONTYPE_LIST">s</field>
        <field name="CURRENCY_LIST">USD</field>
        <field name="BARRIEROFFSETTYPE_LIST">+</field>
        <field name="SECONDBARRIEROFFSETTYPE_LIST">-</field>
        <value name="DURATION">
          <shadow type="math_number" id="1=^4(f;-42YKQ7}qy+.m">
            <field name="NUM">15</field>
          </shadow>
          <block type="variables_get" id="vXFz1Uz6a:{3d7u!`l;x">
            <field name="VAR" id="[ALbnKAase=Els_`)hUl" variabletype="">Sp</field>
          </block>
        </value>
        <value name="AMOUNT">
          <shadow type="math_number" id="RlH$d8eDqTn?LLlcF?7S">
            <field name="NUM">1</field>
          </shadow>
          <block type="variables_get" id="x)7PJ`Te8-BP{9QENWy3">
            <field name="VAR" id="G(73Nc#jgMZ$1;5OU8My" variabletype="">Initial Amount</field>
          </block>
        </value>
      </block>
    </statement>
  </block>
  <block type="tick_analysis" id="oBivoCfdkgt}/4gJ4Q=M" collapsed="true" x="0" y="705">
    <statement name="TICKANALYSIS_STACK">
      <block type="lists_getIndex" id="A~vWNk(:}[FGK!wv;m.a">
        <mutation statement="true" at="false"></mutation>
        <field name="MODE">REMOVE</field>
        <field name="WHERE">FIRST</field>
        <value name="VALUE">
          <block type="variables_get" id="hAFcmOMG[Nu3nCZ7DJ-t">
            <field name="VAR" id="#dZi9;2T@X-Nx|piac!l" variabletype="">promedio_ticks</field>
          </block>
        </value>
        <next>
          <block type="lists_setIndex" id="f^#2zW+i]}#ux1TuFI+`">
            <mutation at="false"></mutation>
            <field name="MODE">INSERT</field>
            <field name="WHERE">LAST</field>
            <value name="LIST">
              <block type="variables_get" id="3Y:!e%w==hpGcF?feKNu">
                <field name="VAR" id="#dZi9;2T@X-Nx|piac!l" variabletype="">promedio_ticks</field>
              </block>
            </value>
            <value name="TO">
              <block type="math_single" id="?pBT?9c/hFhSXeq,n}{n">
                <field name="OP">ABS</field>
                <value name="NUM">
                  <shadow type="math_number" id="A{hd8uh?~owsKX:},#~E">
                    <field name="NUM">9</field>
                  </shadow>
                  <block type="math_arithmetic" id="/=}^n5abY[p7A8|l[Q2p" inline="false">
                    <field name="OP">MINUS</field>
                    <value name="A">
                      <shadow type="math_number" id="D{r[4}i6APj~/`JU$||Z">
                        <field name="NUM">1</field>
                      </shadow>
                      <block type="lists_getIndex" id="[sXSSD:cfvsny]iIt_6p">
                        <mutation statement="false" at="true"></mutation>
                        <field name="MODE">GET</field>
                        <field name="WHERE">FROM_END</field>
                        <value name="VALUE">
                          <block type="ticks" id="n-lz[Rf7vUlU;.A-S,L#"></block>
                        </value>
                        <value name="AT">
                          <block type="math_number" id="LGr^XVsp,4%+QJL.~7Kr">
                            <field name="NUM">1</field>
                          </block>
                        </value>
                      </block>
                    </value>
                    <value name="B">
                      <shadow type="math_number" id="@eof_=)puL~P_K4X=R$,">
                        <field name="NUM">1</field>
                      </shadow>
                      <block type="lists_getIndex" id="^1WLjjfl8L4SQpU;%53Y">
                        <mutation statement="false" at="true"></mutation>
                        <field name="MODE">GET</field>
                        <field name="WHERE">FROM_END</field>
                        <value name="VALUE">
                          <block type="ticks" id="r#g`+t`wE@$N?gJ`DfiP"></block>
                        </value>
                        <value name="AT">
                          <block type="math_number" id="5]6:+g!+WV*ZmnF.Ifr#">
                            <field name="NUM">2</field>
                          </block>
                        </value>
                      </block>
                    </value>
                  </block>
                </value>
              </block>
            </value>
            <next>
              <block type="variables_set" id="Q*%bU[9N_UkpzxjS!GO:">
                <field name="VAR" id="imK2x@=6Mc1~)fsfBWx-" variabletype="">::: Umbral de referencia</field>
                <value name="VALUE">
                  <block type="math_on_list" id="3LS]u!duyN|XC(K0w~h7">
                    <mutation op="AVERAGE"></mutation>
                    <field name="OP">AVERAGE</field>
                    <value name="LIST">
                      <block type="variables_get" id="{?,DC5uHZ7rNNtydq]Zb">
                        <field name="VAR" id="#dZi9;2T@X-Nx|piac!l" variabletype="">promedio_ticks</field>
                      </block>
                    </value>
                  </block>
                </value>
                <next>
                  <block type="variables_set" id="J/.xn!NQ!BfMF%s)I3^w">
                    <field name="VAR" id="Y?yw~SXhjd}Hc/9{;jW4" variabletype="">ema</field>
                    <value name="VALUE">
                      <block type="emaa" id="%}r|{8a1*j?(lV0#[I.T">
                        <value name="INPUT">
                          <block type="ticks" id="Y$/rw4/n=:bq2Lz$Y?~:"></block>
                        </value>
                        <value name="PERIOD">
                          <shadow type="math_number" id="l`*-l]Vn},8ZZU@}9Hvd">
                            <field name="NUM">10</field>
                          </shadow>
                          <block type="math_number" id=";`4k~]L%T{rZ9m3|yh_6">
                            <field name="NUM">14</field>
                          </block>
                        </value>
                      </block>
                    </value>
                    <next>
                      <block type="variables_set" id="M6N}x$qE@J~,bq,Xr98Y">
                        <field name="VAR" id="pwK]FTksg[*.9=~*$|5H" variabletype="">ma</field>
                        <value name="VALUE">
                          <block type="smaa" id="#Mese6Cz,#FpeDJ{`XNK">
                            <value name="INPUT">
                              <block type="ticks" id="*K2S)Y@/SDPE(l,k(!1|"></block>
                            </value>
                            <value name="PERIOD">
                              <shadow type="math_number" id="#q;ib^/jcKT;4cBw:{*/">
                                <field name="NUM">10</field>
                              </shadow>
                              <block type="math_number" id="6{ERxn#q?hLajDP@gN=^">
                                <field name="NUM">14</field>
                              </block>
                            </value>
                          </block>
                        </value>
                      </block>
                    </next>
                  </block>
                </next>
              </block>
            </next>
          </block>
        </next>
      </block>
    </statement>
  </block>
  <block type="before_purchase" id="strategy" x="0" y="758">
    <statement name="BEFOREPURCHASE_STACK">
      <block type="controls_if" id="+8Z8vd0e%7x_o:,Is^Dv" collapsed="true">
        <mutation elseif="1" else="1"></mutation>
        <value name="IF0">
          <block type="logic_operation" id="TdHiAA=j!m$F@6wU-syX">
            <field name="OP">AND</field>
            <value name="A">
              <block type="logic_operation" id="(56gk[8yd4!z=GxUU0[E">
                <field name="OP">AND</field>
                <value name="A">
                  <block type="logic_operation" id="YUmVu.L|G3Ktr[nP7k+O" inline="false" collapsed="true">
                    <field name="OP">AND</field>
                    <value name="A">
                      <block type="logic_compare" id="?bRZFp`@neix?u5q?.Ry" inline="false">
                        <field name="OP">LT</field>
                        <value name="A">
                          <block type="math_single" id="rO_U6HLhhmy2L{D0P_C$">
                            <field name="OP">ABS</field>
                            <value name="NUM">
                              <shadow type="math_number" id="A{hd8uh?~owsKX:},#~E">
                                <field name="NUM">9</field>
                              </shadow>
                              <block type="math_arithmetic" id="~xk/-{.^z[*=ZYggVc]h" inline="false">
                                <field name="OP">MINUS</field>
                                <value name="A">
                                  <shadow type="math_number" id="LhXc68C]O/^TXabFnt@c">
                                    <field name="NUM">1</field>
                                  </shadow>
                                  <block type="lists_getIndex" id="Jsa#)cP6#4)d(/]3N-]n">
                                    <mutation statement="false" at="false"></mutation>
                                    <field name="MODE">GET</field>
                                    <field name="WHERE">LAST</field>
                                    <value name="VALUE">
                                      <block type="variables_get" id="^bLK6~H|V|;{%})?-jYT">
                                        <field name="VAR" id="Y?yw~SXhjd}Hc/9{;jW4" variabletype="">ema</field>
                                      </block>
                                    </value>
                                  </block>
                                </value>
                                <value name="B">
                                  <shadow type="math_number" id="Y@;|lEDjJ,?qQymXGde5">
                                    <field name="NUM">1</field>
                                  </shadow>
                                  <block type="lists_getIndex" id="Hf`HegqRr^9RGkCG)ZWA">
                                    <mutation statement="false" at="false"></mutation>
                                    <field name="MODE">GET</field>
                                    <field name="WHERE">LAST</field>
                                    <value name="VALUE">
                                      <block type="variables_get" id="60]9*d5Cg@*b(zp8wO_*">
                                        <field name="VAR" id="pwK]FTksg[*.9=~*$|5H" variabletype="">ma</field>
                                      </block>
                                    </value>
                                  </block>
                                </value>
                              </block>
                            </value>
                          </block>
                        </value>
                        <value name="B">
                          <block type="math_arithmetic" id="EE[c9a43%n)mfpX3Wq{=">
                            <field name="OP">MULTIPLY</field>
                            <value name="A">
                              <shadow type="math_number" id="tR!K^rnI#4K}s^S++ZNC">
                                <field name="NUM">1</field>
                              </shadow>
                              <block type="math_number" id=".hMMyk:uslpFdliXs`+f">
                                <field name="NUM">0.5</field>
                              </block>
                            </value>
                            <value name="B">
                              <shadow type="math_number" id="WqYjWmNGXqT_y_$hLzWX">
                                <field name="NUM">1</field>
                              </shadow>
                              <block type="variables_get" id="Wj@E6P]Q7HX/(6fnNOEM">
                                <field name="VAR" id="imK2x@=6Mc1~)fsfBWx-" variabletype="">::: Umbral de referencia</field>
                              </block>
                            </value>
                          </block>
                        </value>
                      </block>
                    </value>
                    <value name="B">
                      <block type="logic_compare" id="n)A1th{D57;W5gX?dLB*" inline="false">
                        <field name="OP">GTE</field>
                        <value name="A">
                          <block type="math_single" id="}9t],g-mysGS4Qr?^k-O">
                            <field name="OP">ABS</field>
                            <value name="NUM">
                              <shadow type="math_number" id="A{hd8uh?~owsKX:},#~E">
                                <field name="NUM">9</field>
                              </shadow>
                              <block type="math_arithmetic" id="ylfK?JdbtUE+_;XYTV):" inline="false">
                                <field name="OP">MINUS</field>
                                <value name="A">
                                  <shadow type="math_number" id="LhXc68C]O/^TXabFnt@c">
                                    <field name="NUM">1</field>
                                  </shadow>
                                  <block type="lists_getIndex" id="dx8t/pCxHgocLCx8!,k;">
                                    <mutation statement="false" at="false"></mutation>
                                    <field name="MODE">GET</field>
                                    <field name="WHERE">LAST</field>
                                    <value name="VALUE">
                                      <block type="variables_get" id=":uin1IlX7B:FRm;Ismwv">
                                        <field name="VAR" id="Y?yw~SXhjd}Hc/9{;jW4" variabletype="">ema</field>
                                      </block>
                                    </value>
                                  </block>
                                </value>
                                <value name="B">
                                  <shadow type="math_number" id="Y@;|lEDjJ,?qQymXGde5">
                                    <field name="NUM">1</field>
                                  </shadow>
                                  <block type="lists_getIndex" id="!%0zI{94,)RlG7}kSDGp">
                                    <mutation statement="false" at="false"></mutation>
                                    <field name="MODE">GET</field>
                                    <field name="WHERE">LAST</field>
                                    <value name="VALUE">
                                      <block type="variables_get" id="GAcm*sO.N?*4@bgb1VNU">
                                        <field name="VAR" id="pwK]FTksg[*.9=~*$|5H" variabletype="">ma</field>
                                      </block>
                                    </value>
                                  </block>
                                </value>
                              </block>
                            </value>
                          </block>
                        </value>
                        <value name="B">
                          <block type="math_single" id="BG]/JoWs!KE1p|?yBoGF">
                            <field name="OP">ABS</field>
                            <value name="NUM">
                              <shadow type="math_number" id="A{hd8uh?~owsKX:},#~E">
                                <field name="NUM">9</field>
                              </shadow>
                              <block type="math_arithmetic" id="_ZL5-%0Dyc90MX=vB$u[" inline="false">
                                <field name="OP">MINUS</field>
                                <value name="A">
                                  <shadow type="math_number" id="LhXc68C]O/^TXabFnt@c">
                                    <field name="NUM">1</field>
                                  </shadow>
                                  <block type="lists_getIndex" id="bd,q0{uer_{lmyk,0NIt">
                                    <mutation statement="false" at="true"></mutation>
                                    <field name="MODE">GET</field>
                                    <field name="WHERE">FROM_END</field>
                                    <value name="VALUE">
                                      <block type="variables_get" id=";gM#o_Wi-L.Kdip5zE1M">
                                        <field name="VAR" id="Y?yw~SXhjd}Hc/9{;jW4" variabletype="">ema</field>
                                      </block>
                                    </value>
                                    <value name="AT">
                                      <block type="math_number" id="{IW=ke?-Ui~T[of]1y#T">
                                        <field name="NUM">2</field>
                                      </block>
                                    </value>
                                  </block>
                                </value>
                                <value name="B">
                                  <shadow type="math_number" id="Y@;|lEDjJ,?qQymXGde5">
                                    <field name="NUM">1</field>
                                  </shadow>
                                  <block type="lists_getIndex" id="ut6NW4],:1*1#n-YdcC`">
                                    <mutation statement="false" at="true"></mutation>
                                    <field name="MODE">GET</field>
                                    <field name="WHERE">FROM_END</field>
                                    <value name="VALUE">
                                      <block type="variables_get" id="|5,wvQJUxi|RQGoS^NoK">
                                        <field name="VAR" id="pwK]FTksg[*.9=~*$|5H" variabletype="">ma</field>
                                      </block>
                                    </value>
                                    <value name="AT">
                                      <block type="math_number" id="cT]/AQTWDXU]0.B~j{U2">
                                        <field name="NUM">2</field>
                                      </block>
                                    </value>
                                  </block>
                                </value>
                              </block>
                            </value>
                          </block>
                        </value>
                      </block>
                    </value>
                  </block>
                </value>
                <value name="B">
                  <block type="logic_compare" id="/Jhcimg|Jv$$mXxTv-:#" inline="false" collapsed="true">
                    <field name="OP">GT</field>
                    <value name="A">
                      <block type="tick" id="1$4t__g3os)TtFK^Q7x."></block>
                    </value>
                    <value name="B">
                      <block type="lists_getIndex" id="M|BM(V[n3~C;S2C+id%D">
                        <mutation statement="false" at="false"></mutation>
                        <field name="MODE">GET</field>
                        <field name="WHERE">LAST</field>
                        <value name="VALUE">
                          <block type="variables_get" id="zXS(w6Bw#{PEe9#,up]?">
                            <field name="VAR" id="Y?yw~SXhjd}Hc/9{;jW4" variabletype="">ema</field>
                          </block>
                        </value>
                      </block>
                    </value>
                  </block>
                </value>
              </block>
            </value>
            <value name="B">
              <block type="logic_operation" id="bmrVI77+w#b@]HqA{|6b">
                <field name="OP">AND</field>
                <value name="A">
                  <block type="logic_compare" id="taOj)$NtjLhG|G(rAZ{8">
                    <field name="OP">GT</field>
                    <value name="A">
                      <block type="read_ohlc" id="X5ai1NH^fi,IF(W`/^bm">
                        <field name="OHLCFIELD_LIST">open</field>
                        <field name="CANDLEINTERVAL_LIST">default</field>
                        <value name="CANDLEINDEX">
                          <shadow type="math_number" id="6re9h2aO#$I0v^;K0)[.">
                            <field name="NUM">3</field>
                          </shadow>
                        </value>
                      </block>
                    </value>
                    <value name="B">
                      <block type="read_ohlc" id="SrbJv.@m-B~]CMTOf~2Y">
                        <field name="OHLCFIELD_LIST">close</field>
                        <field name="CANDLEINTERVAL_LIST">default</field>
                        <value name="CANDLEINDEX">
                          <shadow type="math_number" id="(;JHc`Anc`qdBW2Jju3*">
                            <field name="NUM">3</field>
                          </shadow>
                        </value>
                      </block>
                    </value>
                  </block>
                </value>
                <value name="B">
                  <block type="logic_compare" id="2Yjo*e)}k_6`*5qK9^Bi">
                    <field name="OP">GT</field>
                    <value name="A">
                      <block type="read_ohlc" id="B[@~@o(pG~k#g!raKcC6">
                        <field name="OHLCFIELD_LIST">open</field>
                        <field name="CANDLEINTERVAL_LIST">default</field>
                        <value name="CANDLEINDEX">
                          <shadow type="math_number" id="I]kBae~GFaUft27V[SSo">
                            <field name="NUM">2</field>
                          </shadow>
                        </value>
                      </block>
                    </value>
                    <value name="B">
                      <block type="read_ohlc" id="u?vD+GcLF-VFXm]YoypK">
                        <field name="OHLCFIELD_LIST">close</field>
                        <field name="CANDLEINTERVAL_LIST">default</field>
                        <value name="CANDLEINDEX">
                          <shadow type="math_number" id="_1:mIrBmZ?L{XJ}pEWn]">
                            <field name="NUM">2</field>
                          </shadow>
                        </value>
                      </block>
                    </value>
                  </block>
                </value>
              </block>
            </value>
          </block>
        </value>
        <statement name="DO0">
          <block type="variables_set" id="6Cl7Wx-!fXuc1KRbjk7w">
            <field name="VAR" id="(5l7?QBe%F}9JdwBk^!e" variabletype="">ekse</field>
            <value name="VALUE">
              <block type="math_number" id="[^1?PP+M%n8s(t}Yh.[{">
                <field name="NUM">0</field>
              </block>
            </value>
          </block>
        </statement>
        <value name="IF1">
          <block type="logic_operation" id="x+~2Ay$34F6qudQ+5d{p">
            <field name="OP">AND</field>
            <value name="A">
              <block type="logic_compare" id="A~1WF@]]!vEhEsDke}i~">
                <field name="OP">LT</field>
                <value name="A">
                  <block type="read_ohlc" id="+IA@Zf`,$~ZNG`cPZ^XS">
                    <field name="OHLCFIELD_LIST">open</field>
                    <field name="CANDLEINTERVAL_LIST">default</field>
                    <value name="CANDLEINDEX">
                      <shadow type="math_number" id="M2Y4Uy]GWR=h((K#FIA!">
                        <field name="NUM">3</field>
                      </shadow>
                    </value>
                  </block>
                </value>
                <value name="B">
                  <block type="read_ohlc" id="ip*+S4l?t:-2^1zb3,`5">
                    <field name="OHLCFIELD_LIST">close</field>
                    <field name="CANDLEINTERVAL_LIST">default</field>
                    <value name="CANDLEINDEX">
                      <shadow type="math_number" id="O)1dlUH!IIMr4.;l/kbR">
                        <field name="NUM">3</field>
                      </shadow>
                    </value>
                  </block>
                </value>
              </block>
            </value>
            <value name="B">
              <block type="logic_compare" id="#+5EhJ-T*;Vhnc%ik,#l">
                <field name="OP">LT</field>
                <value name="A">
                  <block type="read_ohlc" id="Tk$,-XKY~q{)UASy^)[S">
                    <field name="OHLCFIELD_LIST">open</field>
                    <field name="CANDLEINTERVAL_LIST">default</field>
                    <value name="CANDLEINDEX">
                      <shadow type="math_number" id="vHlFo5?l!CKN`x#=ooQU">
                        <field name="NUM">2</field>
                      </shadow>
                    </value>
                  </block>
                </value>
                <value name="B">
                  <block type="read_ohlc" id="JVvlCh6G7=MHy9]A=pwh">
                    <field name="OHLCFIELD_LIST">close</field>
                    <field name="CANDLEINTERVAL_LIST">default</field>
                    <value name="CANDLEINDEX">
                      <shadow type="math_number" id="vIQT0mWA#;m,c!tA::sC">
                        <field name="NUM">2</field>
                      </shadow>
                    </value>
                  </block>
                </value>
              </block>
            </value>
          </block>
        </value>
        <statement name="DO1">
          <block type="variables_set" id="aL_f}OfRRimEb#Wza%MI">
            <field name="VAR" id="(5l7?QBe%F}9JdwBk^!e" variabletype="">ekse</field>
            <value name="VALUE">
              <block type="math_number" id="H/fUF@-^iKT?$wt;C?QJ">
                <field name="NUM">0</field>
              </block>
            </value>
          </block>
        </statement>
        <statement name="ELSE">
          <block type="variables_set" id="o|5AjVw7nvNfQ93cfp,c">
            <field name="VAR" id="(5l7?QBe%F}9JdwBk^!e" variabletype="">ekse</field>
            <value name="VALUE">
              <block type="math_number" id="OtVj4R3Jxd@T,_M;o8*E">
                <field name="NUM">1</field>
              </block>
            </value>
          </block>
        </statement>
        <next>
          <block type="controls_if" id="M^P?lGMZNCW:%@Cr#Y6m" collapsed="true">
            <mutation else="1"></mutation>
            <value name="IF0">
              <block type="logic_compare" id="RFDJm~KJ6~T0@kdY_~Ch">
                <field name="OP">EQ</field>
                <value name="A">
                  <block type="variables_get" id="T3a{.KZ#aeuVs3QHvEXF">
                    <field name="VAR" id="i:Z4!f)D|*s,oET(5.yJ" variabletype="">logika</field>
                  </block>
                </value>
                <value name="B">
                  <block type="math_number" id="^m]|)1cDNQl2{,Z%z3Cw">
                    <field name="NUM">1</field>
                  </block>
                </value>
              </block>
            </value>
            <statement name="DO0">
              <block type="controls_if" id=",tk2NV]3DjFf^.g{VU^G">
                <mutation elseif="1"></mutation>
                <value name="IF0">
                  <block type="logic_compare" id="k*]D=f}$r425Y3{xm5MY">
                    <field name="OP">GT</field>
                    <value name="A">
                      <block type="read_ohlc" id="[-}OJ~,4z)+MAQFeA+#-">
                        <field name="OHLCFIELD_LIST">open</field>
                        <field name="CANDLEINTERVAL_LIST">default</field>
                        <value name="CANDLEINDEX">
                          <shadow type="math_number" id="T/d~mVV2%_-PU6Dx4DZS">
                            <field name="NUM">2</field>
                          </shadow>
                        </value>
                      </block>
                    </value>
                    <value name="B">
                      <block type="read_ohlc" id="{VjF+qq8}80Tvc;12g7P">
                        <field name="OHLCFIELD_LIST">close</field>
                        <field name="CANDLEINTERVAL_LIST">default</field>
                        <value name="CANDLEINDEX">
                          <shadow type="math_number" id="i6N)hJG!Jmi4CcA_(7.S">
                            <field name="NUM">2</field>
                          </shadow>
                        </value>
                      </block>
                    </value>
                  </block>
                </value>
                <statement name="DO0">
                  <block type="controls_if" id="mZx_ID-f%mx+|8DsYcJO" collapsed="true">
                    <mutation elseif="1" else="1"></mutation>
                    <value name="IF0">
                      <block type="logic_compare" id="84]XziaO)~7-kPR7o)l1">
                        <field name="OP">LT</field>
                        <value name="A">
                          <block type="read_ohlc" id="bn9cq~urE[hfW1Afa#hi">
                            <field name="OHLCFIELD_LIST">open</field>
                            <field name="CANDLEINTERVAL_LIST">default</field>
                            <value name="CANDLEINDEX">
                              <shadow type="math_number" id="hKRl~~Ieufic(INi4Fx_">
                                <field name="NUM">1</field>
                              </shadow>
                            </value>
                          </block>
                        </value>
                        <value name="B">
                          <block type="read_ohlc" id="=(fessIvRP)KNX8*z2U]">
                            <field name="OHLCFIELD_LIST">close</field>
                            <field name="CANDLEINTERVAL_LIST">default</field>
                            <value name="CANDLEINDEX">
                              <shadow type="math_number" id="Nb4.X=Pfr^xP=Xbr2/jT">
                                <field name="NUM">1</field>
                              </shadow>
                            </value>
                          </block>
                        </value>
                      </block>
                    </value>
                    <statement name="DO0">
                      <block type="notify" id="_{nt=FX4KJSb5GG7W$*A">
                        <field name="NOTIFICATION_TYPE">error</field>
                        <field name="NOTIFICATION_SOUND">silent</field>
                        <value name="MESSAGE">
                          <shadow type="text" id="b3;oBH6/g-Dz7;5]`wP:">
                            <field name="TEXT">Se viene una operación a la Baja....</field>
                          </shadow>
                        </value>
                      </block>
                    </statement>
                    <value name="IF1">
                      <block type="logic_compare" id="09c`SI6$umGpoD]XWGs5">
                        <field name="OP">GT</field>
                        <value name="A">
                          <block type="read_ohlc" id="KkoMv$0|#+DsccU`a@r,">
                            <field name="OHLCFIELD_LIST">open</field>
                            <field name="CANDLEINTERVAL_LIST">default</field>
                            <value name="CANDLEINDEX">
                              <shadow type="math_number" id=".?hU|]d/QeQE8L2+qna9">
                                <field name="NUM">1</field>
                              </shadow>
                            </value>
                          </block>
                        </value>
                        <value name="B">
                          <block type="read_ohlc" id="2j^W%W9g;f}_!R?HwG;`">
                            <field name="OHLCFIELD_LIST">close</field>
                            <field name="CANDLEINTERVAL_LIST">default</field>
                            <value name="CANDLEINDEX">
                              <shadow type="math_number" id="+rk,1Gm!Vb}nb#3-2D[N">
                                <field name="NUM">1</field>
                              </shadow>
                            </value>
                          </block>
                        </value>
                      </block>
                    </value>
                    <statement name="DO1">
                      <block type="notify" id="A!D@B=gg6FN])PG.=.~a">
                        <field name="NOTIFICATION_TYPE">error</field>
                        <field name="NOTIFICATION_SOUND">silent</field>
                        <value name="MESSAGE">
                          <shadow type="text" id="+u0X=y0C?ly!F!$s36sn">
                            <field name="TEXT">Se viene una operación a la Baja....</field>
                          </shadow>
                        </value>
                      </block>
                    </statement>
                    <statement name="ELSE">
                      <block type="controls_if" id="a}2c`2gZa1Aaq#)8wRhy">
                        <mutation else="1"></mutation>
                        <value name="IF0">
                          <block type="logic_compare" id="?xZmmQkFeEMOg|5qZ_z]">
                            <field name="OP">LT</field>
                            <value name="A">
                              <block type="read_ohlc" id=";*3zX6%V]6hZAT:yUTZj">
                                <field name="OHLCFIELD_LIST">open</field>
                                <field name="CANDLEINTERVAL_LIST">default</field>
                                <value name="CANDLEINDEX">
                                  <shadow type="math_number" id="k9k*=T|8z-{8.p6oRp42">
                                    <field name="NUM">1</field>
                                  </shadow>
                                </value>
                              </block>
                            </value>
                            <value name="B">
                              <block type="tick" id="Tg.wgiE+.IW6Wzo)+!Vc"></block>
                            </value>
                          </block>
                        </value>
                        <statement name="DO0">
                          <block type="notify" id="GGZ?ubl(4pM1nhwZ8qEK">
                            <field name="NOTIFICATION_TYPE">error</field>
                            <field name="NOTIFICATION_SOUND">silent</field>
                            <value name="MESSAGE">
                              <shadow type="text" id="{~L#r?,CI,kVu%at|06B">
                                <field name="TEXT">Se viene una operación a la Baja....</field>
                              </shadow>
                            </value>
                          </block>
                        </statement>
                        <statement name="ELSE">
                          <block type="variables_set" id="_^Z+*2?ry0%5sql1$,[=">
                            <field name="VAR" id="o/=0QCkDSD0FNOZ4LUcH" variabletype="">posisi</field>
                            <value name="VALUE">
                              <block type="math_number" id="$*F;nIp4l0(`,88~C9Y2">
                                <field name="NUM">2</field>
                              </block>
                            </value>
                            <next>
                              <block type="purchase" id="[XM|WE[{Ym0ui,SU.}U[">
                                <field name="PURCHASE_LIST">PUT</field>
                              </block>
                            </next>
                          </block>
                        </statement>
                      </block>
                    </statement>
                  </block>
                </statement>
                <value name="IF1">
                  <block type="logic_compare" id="==1_|{TAw[40h!z@8wou">
                    <field name="OP">LT</field>
                    <value name="A">
                      <block type="read_ohlc" id="3PlS5NF6xDE}Rv]{BZ^~">
                        <field name="OHLCFIELD_LIST">open</field>
                        <field name="CANDLEINTERVAL_LIST">default</field>
                        <value name="CANDLEINDEX">
                          <shadow type="math_number" id="|L#J|YDS3uBSElp{`Yiu">
                            <field name="NUM">2</field>
                          </shadow>
                        </value>
                      </block>
                    </value>
                    <value name="B">
                      <block type="read_ohlc" id="gkVH7d]@4v?;b12g47pQ">
                        <field name="OHLCFIELD_LIST">close</field>
                        <field name="CANDLEINTERVAL_LIST">default</field>
                        <value name="CANDLEINDEX">
                          <shadow type="math_number" id="-Hy%a[@N2[*1;c1.1Z8e">
                            <field name="NUM">2</field>
                          </shadow>
                        </value>
                      </block>
                    </value>
                  </block>
                </value>
                <statement name="DO1">
                  <block type="controls_if" id="v?Il8FVKfjRhP8Z*/H{J" collapsed="true">
                    <mutation elseif="1" else="1"></mutation>
                    <value name="IF0">
                      <block type="logic_compare" id="HV1RDc`utUO%dx|:pSZQ">
                        <field name="OP">GT</field>
                        <value name="A">
                          <block type="read_ohlc" id="Zd1Hc!c5Yibqh(J*vr{X">
                            <field name="OHLCFIELD_LIST">open</field>
                            <field name="CANDLEINTERVAL_LIST">default</field>
                            <value name="CANDLEINDEX">
                              <shadow type="math_number" id="U2/umRDMd6)+tcc6!/HE">
                                <field name="NUM">1</field>
                              </shadow>
                            </value>
                          </block>
                        </value>
                        <value name="B">
                          <block type="read_ohlc" id="ia~2}DDjbf?r^Qw#3A)n">
                            <field name="OHLCFIELD_LIST">close</field>
                            <field name="CANDLEINTERVAL_LIST">default</field>
                            <value name="CANDLEINDEX">
                              <shadow type="math_number" id="T!m(E37Wqo_-W1N9R16E">
                                <field name="NUM">1</field>
                              </shadow>
                            </value>
                          </block>
                        </value>
                      </block>
                    </value>
                    <statement name="DO0">
                      <block type="notify" id="6P)9B5T#Nvf8mBVEDz0v">
                        <field name="NOTIFICATION_TYPE">success</field>
                        <field name="NOTIFICATION_SOUND">silent</field>
                        <value name="MESSAGE">
                          <shadow type="text" id="xa+GV`=#tcd8Si}h@EcT">
                            <field name="TEXT">Se viene una operación al Alza....</field>
                          </shadow>
                        </value>
                      </block>
                    </statement>
                    <value name="IF1">
                      <block type="logic_compare" id="uuHK+1Jo*T|0H1|B34:]">
                        <field name="OP">LT</field>
                        <value name="A">
                          <block type="read_ohlc" id="-mymNNvx+(^Na5qV[oFl">
                            <field name="OHLCFIELD_LIST">open</field>
                            <field name="CANDLEINTERVAL_LIST">default</field>
                            <value name="CANDLEINDEX">
                              <shadow type="math_number" id="Q%LPp+Jin5.W%z21(:OP">
                                <field name="NUM">1</field>
                              </shadow>
                            </value>
                          </block>
                        </value>
                        <value name="B">
                          <block type="read_ohlc" id=".KWV!M9xm#K)5s2F@Mg$">
                            <field name="OHLCFIELD_LIST">close</field>
                            <field name="CANDLEINTERVAL_LIST">default</field>
                            <value name="CANDLEINDEX">
                              <shadow type="math_number" id="-ys;!t:xylwhsfK]e39y">
                                <field name="NUM">1</field>
                              </shadow>
                            </value>
                          </block>
                        </value>
                      </block>
                    </value>
                    <statement name="DO1">
                      <block type="notify" id="EWZz6/:2x:4^Z_UND?SF">
                        <field name="NOTIFICATION_TYPE">success</field>
                        <field name="NOTIFICATION_SOUND">silent</field>
                        <value name="MESSAGE">
                          <shadow type="text" id="Z?e+_;2G(AO=GkM-oI}g">
                            <field name="TEXT">Se viene una operación al Alza....</field>
                          </shadow>
                        </value>
                      </block>
                    </statement>
                    <statement name="ELSE">
                      <block type="controls_if" id="8$nl|Zo*=/?GM8O?DBxO">
                        <mutation else="1"></mutation>
                        <value name="IF0">
                          <block type="logic_compare" id="|$C%:)kvnf#_8k(60n{)">
                            <field name="OP">GT</field>
                            <value name="A">
                              <block type="read_ohlc" id="5cVk^=^7kfbO6#w5n=Sr">
                                <field name="OHLCFIELD_LIST">open</field>
                                <field name="CANDLEINTERVAL_LIST">default</field>
                                <value name="CANDLEINDEX">
                                  <shadow type="math_number" id="Ii=Wf2X%|Q||d(g}6dXp">
                                    <field name="NUM">1</field>
                                  </shadow>
                                </value>
                              </block>
                            </value>
                            <value name="B">
                              <block type="tick" id="o*H+7Jq[5*1V3vqrN%-#"></block>
                            </value>
                          </block>
                        </value>
                        <statement name="DO0">
                          <block type="notify" id="$5?QW%kIvqLNLC;`p}=~">
                            <field name="NOTIFICATION_TYPE">success</field>
                            <field name="NOTIFICATION_SOUND">silent</field>
                            <value name="MESSAGE">
                              <shadow type="text" id="R3:bUc^P|_7mI_AC0xLJ">
                                <field name="TEXT">Se viene una operación al Alza....</field>
                              </shadow>
                            </value>
                          </block>
                        </statement>
                        <statement name="ELSE">
                          <block type="variables_set" id="f3p;|1L`%q#ebNA8wZp-">
                            <field name="VAR" id="o/=0QCkDSD0FNOZ4LUcH" variabletype="">posisi</field>
                            <value name="VALUE">
                              <block type="math_number" id="`q0gCXy+vUE,f;yqJ-[u">
                                <field name="NUM">1</field>
                              </block>
                            </value>
                            <next>
                              <block type="purchase" id="%5#,.07tN!M;jNp?%B@q">
                                <field name="PURCHASE_LIST">CALL</field>
                              </block>
                            </next>
                          </block>
                        </statement>
                      </block>
                    </statement>
                  </block>
                </statement>
              </block>
            </statement>
            <statement name="ELSE">
              <block type="controls_if" id="cZ@V$R@JJSZE4iuX*#+v">
                <mutation elseif="1"></mutation>
                <value name="IF0">
                  <block type="logic_compare" id="_jeklacE9RLqDsV^V3Yn">
                    <field name="OP">GT</field>
                    <value name="A">
                      <block type="read_ohlc" id="FZ_swrA3vt3qsa,wyIZT">
                        <field name="OHLCFIELD_LIST">open</field>
                        <field name="CANDLEINTERVAL_LIST">default</field>
                        <value name="CANDLEINDEX">
                          <shadow type="math_number" id="}ildM5!Hk}N]Y4Q!8tT6">
                            <field name="NUM">2</field>
                          </shadow>
                        </value>
                      </block>
                    </value>
                    <value name="B">
                      <block type="read_ohlc" id="hk8zj;MtZ#kY-n~i?@ZT">
                        <field name="OHLCFIELD_LIST">close</field>
                        <field name="CANDLEINTERVAL_LIST">default</field>
                        <value name="CANDLEINDEX">
                          <shadow type="math_number" id=")=RU,8u-4wlsQ(2{EnhW">
                            <field name="NUM">2</field>
                          </shadow>
                        </value>
                      </block>
                    </value>
                  </block>
                </value>
                <statement name="DO0">
                  <block type="controls_if" id=":X#%tf1fA=R%mUbFV+X]" collapsed="true">
                    <mutation elseif="1" else="1"></mutation>
                    <value name="IF0">
                      <block type="logic_compare" id="VA=/1`n][WQW7dLmNi1V">
                        <field name="OP">LT</field>
                        <value name="A">
                          <block type="read_ohlc" id="/56VG^+:!0B3X`OzY)7l">
                            <field name="OHLCFIELD_LIST">open</field>
                            <field name="CANDLEINTERVAL_LIST">default</field>
                            <value name="CANDLEINDEX">
                              <shadow type="math_number" id="(q7SR9sP@aZMIqQiC,?N">
                                <field name="NUM">1</field>
                              </shadow>
                            </value>
                          </block>
                        </value>
                        <value name="B">
                          <block type="read_ohlc" id="E@T~qrA*@IU=vX34u[/t">
                            <field name="OHLCFIELD_LIST">close</field>
                            <field name="CANDLEINTERVAL_LIST">default</field>
                            <value name="CANDLEINDEX">
                              <shadow type="math_number" id="23dAxIT%EKxJq3LcLrcj">
                                <field name="NUM">1</field>
                              </shadow>
                            </value>
                          </block>
                        </value>
                      </block>
                    </value>
                    <statement name="DO0">
                      <block type="notify" id="-DiLC6Ied9R;Zp]xlV{=">
                        <field name="NOTIFICATION_TYPE">success</field>
                        <field name="NOTIFICATION_SOUND">silent</field>
                        <value name="MESSAGE">
                          <shadow type="text" id=",y)NcHZYe|DDW=g`Vdy6">
                            <field name="TEXT">Se viene una operación al Alza....</field>
                          </shadow>
                        </value>
                      </block>
                    </statement>
                    <value name="IF1">
                      <block type="logic_compare" id="d1M?k$^H[2;W1mFg9b=n">
                        <field name="OP">GT</field>
                        <value name="A">
                          <block type="read_ohlc" id="]`=:+#(q4Jj4C]~k0{F}">
                            <field name="OHLCFIELD_LIST">open</field>
                            <field name="CANDLEINTERVAL_LIST">default</field>
                            <value name="CANDLEINDEX">
                              <shadow type="math_number" id=",,xs,q8JqKJH{0SBwMfX">
                                <field name="NUM">1</field>
                              </shadow>
                            </value>
                          </block>
                        </value>
                        <value name="B">
                          <block type="read_ohlc" id="BGP)EDn8T*lFwlj;aU3$">
                            <field name="OHLCFIELD_LIST">close</field>
                            <field name="CANDLEINTERVAL_LIST">default</field>
                            <value name="CANDLEINDEX">
                              <shadow type="math_number" id="k/J^L9}OFmUpd2V@iE5q">
                                <field name="NUM">1</field>
                              </shadow>
                            </value>
                          </block>
                        </value>
                      </block>
                    </value>
                    <statement name="DO1">
                      <block type="notify" id="LYLT(dC+g@`K0RvWGQ0;">
                        <field name="NOTIFICATION_TYPE">success</field>
                        <field name="NOTIFICATION_SOUND">silent</field>
                        <value name="MESSAGE">
                          <shadow type="text" id="UfvFwg_1z4gYQ+aiw=iW">
                            <field name="TEXT">Se viene una operación al Alza....</field>
                          </shadow>
                        </value>
                      </block>
                    </statement>
                    <statement name="ELSE">
                      <block type="purchase" id="I@X=D6(V:UI%g4b.lgVD">
                        <field name="PURCHASE_LIST">CALL</field>
                      </block>
                    </statement>
                  </block>
                </statement>
                <value name="IF1">
                  <block type="logic_compare" id="+%1UR5c9cxjg/jXnYPXZ">
                    <field name="OP">LT</field>
                    <value name="A">
                      <block type="read_ohlc" id="-^0i/FbizbSt-|gDhn#$">
                        <field name="OHLCFIELD_LIST">open</field>
                        <field name="CANDLEINTERVAL_LIST">default</field>
                        <value name="CANDLEINDEX">
                          <shadow type="math_number" id="ngU,tG[]ZEVFQEQf%Mvc">
                            <field name="NUM">2</field>
                          </shadow>
                        </value>
                      </block>
                    </value>
                    <value name="B">
                      <block type="read_ohlc" id="cvJk3`6-:Ed=0zV-]-rz">
                        <field name="OHLCFIELD_LIST">close</field>
                        <field name="CANDLEINTERVAL_LIST">default</field>
                        <value name="CANDLEINDEX">
                          <shadow type="math_number" id="mE}wRW2uYF}HI^+bM1Ue">
                            <field name="NUM">2</field>
                          </shadow>
                        </value>
                      </block>
                    </value>
                  </block>
                </value>
                <statement name="DO1">
                  <block type="controls_if" id="(_n%L{@u702RS9C,Z#@," collapsed="true">
                    <mutation elseif="1" else="1"></mutation>
                    <value name="IF0">
                      <block type="logic_compare" id="T2*XUY%a5THNQ[6N5xKD">
                        <field name="OP">GT</field>
                        <value name="A">
                          <block type="read_ohlc" id="rqFq,@iyRj?kc4_NoIhB">
                            <field name="OHLCFIELD_LIST">open</field>
                            <field name="CANDLEINTERVAL_LIST">default</field>
                            <value name="CANDLEINDEX">
                              <shadow type="math_number" id="Myg$Hg_T%9s3u81Zk/B2">
                                <field name="NUM">1</field>
                              </shadow>
                            </value>
                          </block>
                        </value>
                        <value name="B">
                          <block type="read_ohlc" id="9|;pqiB.|+pM)yX]lXD2">
                            <field name="OHLCFIELD_LIST">close</field>
                            <field name="CANDLEINTERVAL_LIST">default</field>
                            <value name="CANDLEINDEX">
                              <shadow type="math_number" id="Wy{t?nza4SMbxk83W=WT">
                                <field name="NUM">1</field>
                              </shadow>
                            </value>
                          </block>
                        </value>
                      </block>
                    </value>
                    <statement name="DO0">
                      <block type="notify" id="sE:n$is*|u7vh.jz(4n5">
                        <field name="NOTIFICATION_TYPE">error</field>
                        <field name="NOTIFICATION_SOUND">silent</field>
                        <value name="MESSAGE">
                          <shadow type="text" id="ER8Ax~or]%k1@7,PcnNR">
                            <field name="TEXT">Se viene una operación a la Baja....</field>
                          </shadow>
                        </value>
                      </block>
                    </statement>
                    <value name="IF1">
                      <block type="logic_compare" id="d_?bj__j!;]aGlVLm8K6">
                        <field name="OP">LT</field>
                        <value name="A">
                          <block type="read_ohlc" id="1;cDO_m%xd#}kUe]M95d">
                            <field name="OHLCFIELD_LIST">open</field>
                            <field name="CANDLEINTERVAL_LIST">default</field>
                            <value name="CANDLEINDEX">
                              <shadow type="math_number" id="1~l|:LOA=f8kyDuREk?b">
                                <field name="NUM">1</field>
                              </shadow>
                            </value>
                          </block>
                        </value>
                        <value name="B">
                          <block type="read_ohlc" id=")B:9!:EH1%=hx8,~.[})">
                            <field name="OHLCFIELD_LIST">close</field>
                            <field name="CANDLEINTERVAL_LIST">default</field>
                            <value name="CANDLEINDEX">
                              <shadow type="math_number" id="K[yX:Rxsc~Uijo+WwkU%">
                                <field name="NUM">1</field>
                              </shadow>
                            </value>
                          </block>
                        </value>
                      </block>
                    </value>
                    <statement name="DO1">
                      <block type="notify" id="=3;@O-4;N#Yq%kPOuMmv">
                        <field name="NOTIFICATION_TYPE">error</field>
                        <field name="NOTIFICATION_SOUND">silent</field>
                        <value name="MESSAGE">
                          <shadow type="text" id="Ks6oSaTDkd]vf:RNn.@C">
                            <field name="TEXT">Se viene una operación a la Baja....</field>
                          </shadow>
                        </value>
                      </block>
                    </statement>
                    <statement name="ELSE">
                      <block type="purchase" id="GmF1SuTAU:ToO[$F-MLw">
                        <field name="PURCHASE_LIST">PUT</field>
                      </block>
                    </statement>
                  </block>
                </statement>
              </block>
            </statement>
          </block>
        </next>
      </block>
    </statement>
  </block>
  <block type="after_purchase" id="Vt,CkLeK8E?%BmnB`~M)" collapsed="true" x="2" y="884">
    <statement name="AFTERPURCHASE_STACK">
      <block type="controls_if" id="h8mS;G*3He=SI[_JfZcG">
        <mutation else="1"></mutation>
        <value name="IF0">
          <block type="contract_check_result" id="sy^PHd0k*7y5(KK`m?E!" collapsed="true">
            <field name="CHECK_RESULT">win</field>
          </block>
        </value>
        <statement name="DO0">
          <block type="variables_set" id="`s/oy+RRZ~!m0.AkV8Fy" collapsed="true">
            <field name="VAR" id="7([F3U3H^l{pMDX9r(WZ" variabletype="">Jloss</field>
            <value name="VALUE">
              <block type="math_number" id="_{owG{`$_`Pg5kC6}j}Z">
                <field name="NUM">0</field>
              </block>
            </value>
            <next>
              <block type="variables_set" id="{(ouCRN{c{;WS,%rVOU." collapsed="true">
                <field name="VAR" id="i:Z4!f)D|*s,oET(5.yJ" variabletype="">logika</field>
                <value name="VALUE">
                  <block type="math_number" id="ILp|KVxFsEOyfXFyXf[~">
                    <field name="NUM">1</field>
                  </block>
                </value>
                <next>
                  <block type="variables_set" id="=No:sebl=.YR{;8::)P!" collapsed="true">
                    <field name="VAR" id="G(73Nc#jgMZ$1;5OU8My" variabletype="">Initial Amount</field>
                    <value name="VALUE">
                      <block type="variables_get" id="#7_n$FOMR`UH|)43pC`l">
                        <field name="VAR" id="+1/Ux:bV9I$!t23w54JE" variabletype="">La inversión será:</field>
                      </block>
                    </value>
                  </block>
                </next>
              </block>
            </next>
          </block>
        </statement>
        <statement name="ELSE">
          <block type="controls_if" id="5=`eE?Yr$a3q`W,7E@ua">
            <mutation else="1"></mutation>
            <value name="IF0">
              <block type="logic_compare" id="URfUvMw6RH1!owco6N[V">
                <field name="OP">LTE</field>
                <value name="A">
                  <block type="variables_get" id="unMm]Y^?*OD:5k4I10Ff">
                    <field name="VAR" id="7([F3U3H^l{pMDX9r(WZ" variabletype="">Jloss</field>
                  </block>
                </value>
                <value name="B">
                  <block type="math_number" id="3+I,`fMc5yUKe9yz{FSS">
                    <field name="NUM">15</field>
                  </block>
                </value>
              </block>
            </value>
            <statement name="DO0">
              <block type="variables_set" id="dQW(B_m2@@fLZJe9g7u:">
                <field name="VAR" id="7([F3U3H^l{pMDX9r(WZ" variabletype="">Jloss</field>
                <value name="VALUE">
                  <block type="math_arithmetic" id="E|N1WB8Q`2j}HAWePN5Q">
                    <field name="OP">ADD</field>
                    <value name="A">
                      <shadow type="math_number" id="VQ-h1Rr]qd$_.^CbUI;+">
                        <field name="NUM">1</field>
                      </shadow>
                      <block type="variables_get" id="iqR].kR1FKEB_^d#^+e9">
                        <field name="VAR" id="7([F3U3H^l{pMDX9r(WZ" variabletype="">Jloss</field>
                      </block>
                    </value>
                    <value name="B">
                      <shadow type="math_number" id="l#9+vg3fFK*duie`}LZZ">
                        <field name="NUM">1</field>
                      </shadow>
                      <block type="math_number" id="Qc(Y`,at./)2e#n$enxj">
                        <field name="NUM">1</field>
                      </block>
                    </value>
                  </block>
                </value>
              </block>
            </statement>
            <statement name="ELSE">
              <block type="variables_set" id="mlyR2NnL2RzCN//R9ry)">
                <field name="VAR" id="i:Z4!f)D|*s,oET(5.yJ" variabletype="">logika</field>
                <value name="VALUE">
                  <block type="math_number" id="HFj(op}D!k(zH5H.8PGE">
                    <field name="NUM">2</field>
                  </block>
                </value>
              </block>
            </statement>
            <next>
              <block type="math_change" id="6+eo9mB-g5!Q}@N1;9Vf">
                <field name="VAR" id="G(73Nc#jgMZ$1;5OU8My" variabletype="">Initial Amount</field>
                <value name="DELTA">
                  <shadow type="math_number" id="N=Vo^MVz~/^(xt7Ag@8E">
                    <field name="NUM">1</field>
                  </shadow>
                  <block type="math_arithmetic" id="n:OFfXlnqOV81,Ufo[}j">
                    <field name="OP">MULTIPLY</field>
                    <value name="A">
                      <shadow type="math_number" id="ka8n8|Dugz,q5FkUjs`7">
                        <field name="NUM">1</field>
                      </shadow>
                      <block type="math_single" id="*;N@Ve,Wv|$953Li.0n^">
                        <field name="OP">ABS</field>
                        <value name="NUM">
                          <shadow type="math_number" id="GleSn`9j7Cm7/dqg}FIA">
                            <field name="NUM">9</field>
                          </shadow>
                          <block type="read_details" id="bx4Nu:=)x6h_fAAegJ+/">
                            <field name="DETAIL_INDEX">4</field>
                          </block>
                        </value>
                      </block>
                    </value>
                    <value name="B">
                      <shadow type="math_number" id="{JXdZCp2%s=sfO@yN:n}">
                        <field name="NUM">1</field>
                      </shadow>
                      <block type="math_number" id="-m(S4tRKA-#29Wv;8+|[">
                        <field name="NUM">1.041</field>
                      </block>
                    </value>
                  </block>
                </value>
                <next>
                  <block type="controls_if" id="TM@6zOX8P=;]5N:]r2nB" collapsed="true">
                    <value name="IF0">
                      <block type="logic_compare" id="tc1ttkD^LwToN7Y(%#us">
                        <field name="OP">GTE</field>
                        <value name="A">
                          <block type="math_single" id="=a*u_+k0k#,+4CLuA`RP">
                            <field name="OP">ABS</field>
                            <value name="NUM">
                              <shadow type="math_number" id="ft^DVzOH^GlSjzUC}@3c">
                                <field name="NUM">9</field>
                              </shadow>
                              <block type="read_details" id="EJZClLSm$oEEkF~gNVwS">
                                <field name="DETAIL_INDEX">4</field>
                              </block>
                            </value>
                          </block>
                        </value>
                        <value name="B">
                          <block type="variables_get" id="2P@FcU,g2FlJU4*r#65l">
                            <field name="VAR" id="a;P]ajpvJ|Wzma0#|Kzd" variabletype="">Estoy dispuesto a perder:</field>
                          </block>
                        </value>
                      </block>
                    </value>
                    <statement name="DO0">
                      <block type="variables_set" id="asAOg=oShw4Q%:fU.,;O">
                        <field name="VAR" id="G(73Nc#jgMZ$1;5OU8My" variabletype="">Initial Amount</field>
                        <value name="VALUE">
                          <block type="variables_get" id="fI4P.5Yz;G;]Q~R|{SqJ">
                            <field name="VAR" id="+1/Ux:bV9I$!t23w54JE" variabletype="">La inversión será:</field>
                          </block>
                        </value>
                      </block>
                    </statement>
                  </block>
                </next>
              </block>
            </next>
          </block>
        </statement>
        <next>
          <block type="controls_if" id="mLdstq!9N%:2{D2[QG+U" collapsed="true">
            <mutation elseif="1"></mutation>
            <value name="IF0">
              <block type="logic_compare" id="y~]#5VITArcQ(WCsI6^h">
                <field name="OP">GTE</field>
                <value name="A">
                  <block type="total_profit" id=";!euAo,Dk5`Ip^z]YD6Z"></block>
                </value>
                <value name="B">
                  <block type="variables_get" id="+#T:=240-8Sc(P`fTi?C">
                    <field name="VAR" id="=1$vClxY+2pTTnp]@oAR" variabletype="">Quiero Ganar:</field>
                  </block>
                </value>
              </block>
            </value>
            <statement name="DO0">
              <block type="text_print" id="xsw/WX4M!yznEeN#p)Xj" collapsed="true">
                <value name="TEXT">
                  <shadow type="text" id="kqlrIk.GO.^}hI,PoUV)">
                    <field name="TEXT">abc</field>
                  </shadow>
                  <block type="text_join" id="Tnu}_m$|6F!/?ZyMvvcU">
                    <mutation items="2"></mutation>
                    <value name="ADD0">
                      <block type="text" id="pC6@4D=*UD1.huxywltV">
                        <field name="TEXT">SIIIIII LO LOGRAMOS. GANAMOS:</field>
                      </block>
                    </value>
                    <value name="ADD1">
                      <block type="total_profit" id="^(Y=R`9*%|X:hZkaf]%u"></block>
                    </value>
                  </block>
                </value>
              </block>
            </statement>
            <value name="IF1">
              <block type="logic_compare" id="e*6F05?saFS+h#ME2/o[">
                <field name="OP">LT</field>
                <value name="A">
                  <block type="total_profit" id="S0zfBV?byD;]Uh;Ul$G:"></block>
                </value>
                <value name="B">
                  <block type="variables_get" id="E6Y6-.z)UHJN~!1/ZJG-">
                    <field name="VAR" id="=1$vClxY+2pTTnp]@oAR" variabletype="">Quiero Ganar:</field>
                  </block>
                </value>
              </block>
            </value>
            <statement name="DO1">
              <block type="controls_if" id="}D~ZoAUGBRwxnqa_,w4A">
                <mutation else="1"></mutation>
                <value name="IF0">
                  <block type="logic_operation" id="@rneRa]_|DW:)S}a??({">
                    <field name="OP">AND</field>
                    <value name="A">
                      <block type="math_number_property" id="@KNpabc/e19P^BO`G7q7">
                        <mutation divisor_input="false"></mutation>
                        <field name="PROPERTY">NEGATIVE</field>
                        <value name="NUMBER_TO_CHECK">
                          <shadow type="math_number" id="O5EG^Jmug}%}_rFum%xH">
                            <field name="NUM">0</field>
                          </shadow>
                          <block type="total_profit" id="P$h*PE7H_7$j?hJ|~l_f"></block>
                        </value>
                      </block>
                    </value>
                    <value name="B">
                      <block type="logic_compare" id="[dBJs*{}2c3gdg!az{Ik">
                        <field name="OP">GTE</field>
                        <value name="A">
                          <block type="math_single" id="T5iLK1|mN)/sP78QD@A*">
                            <field name="OP">ABS</field>
                            <value name="NUM">
                              <shadow type="math_number" id="GleSn`9j7Cm7/dqg}FIA">
                                <field name="NUM">9</field>
                              </shadow>
                              <block type="total_profit" id="R4t(}@EGxo@-Tue]9;Z["></block>
                            </value>
                          </block>
                        </value>
                        <value name="B">
                          <block type="variables_get" id="u`.)E!cyC=Dc1Q)U7N[T">
                            <field name="VAR" id="a;P]ajpvJ|Wzma0#|Kzd" variabletype="">Estoy dispuesto a perder:</field>
                          </block>
                        </value>
                      </block>
                    </value>
                  </block>
                </value>
                <statement name="DO0">
                  <block type="text_print" id="Z!JNOz1K;[a~=6J!ti1/" collapsed="true">
                    <value name="TEXT">
                      <shadow type="text" id="|D(=r=owZnk,lmxkNk%3">
                        <field name="TEXT">abc</field>
                      </shadow>
                      <block type="text_join" id="|+nl9@.-+;6~=`|u9}zq">
                        <mutation items="2"></mutation>
                        <value name="ADD0">
                          <block type="text" id="]S,oa~qfAWwbO;BD3zSA">
                            <field name="TEXT">Lo siento. Perdimos:</field>
                          </block>
                        </value>
                        <value name="ADD1">
                          <block type="total_profit" id=":|rV9@Y^CO-YtK%{oX^R"></block>
                        </value>
                      </block>
                    </value>
                  </block>
                </statement>
                <statement name="ELSE">
                  <block type="trade_again" id="H2leW}F^Z(ECR;),p$Md"></block>
                </statement>
              </block>
            </statement>
            <next>
              <block type="variables_set" id="S?{@_S42lYBg4oN(FV[^" collapsed="true">
                <field name="VAR" id="[ALbnKAase=Els_`)hUl" variabletype="">Sp</field>
                <value name="VALUE">
                  <block type="math_number" id="JYw?8}0y%ZKm5N9ir8tr">
                    <field name="NUM">15</field>
                  </block>
                </value>
              </block>
            </next>
          </block>
        </next>
      </block>
    </statement>
  </block>
  <block type="tick_analysis" id="(Eu/9^i~go*WY-G$j`:d" collapsed="true" x="2" y="938">
    <statement name="TICKANALYSIS_STACK">
      <block type="timeout" id="O8*E1=Jp.EIYpy5!10{5">
        <statement name="TIMEOUTSTACK">
          <block type="notify" id="Ucla)hNEpc3)z7(F@140">
            <field name="NOTIFICATION_TYPE">info</field>
            <field name="NOTIFICATION_SOUND">silent</field>
            <value name="MESSAGE">
              <shadow type="text" id="bS;F^}Ll+,xKDHpHCF1j">
                <field name="TEXT">Paciencia, Estamos trababajando...</field>
              </shadow>
            </value>
          </block>
        </statement>
        <value name="SECONDS">
          <shadow type="math_number" id="=IB)zO}$Oj[;%Mp:u%LE">
            <field name="NUM">5</field>
          </shadow>
        </value>
      </block>
    </statement>
  </block>
  <block type="during_purchase" id="A}S;f)]6p2GN`*HD%7uu" x="5" y="1002">
    <statement name="DURING_PURCHASE_STACK">
      <block type="controls_if" id="v;hrtNIMP[1RBO3vNq1U" collapsed="true">
        <value name="IF0">
          <block type="logic_compare" id="$?xVi^%~$_j=cPl3y%}}">
            <field name="OP">EQ</field>
            <value name="A">
              <block type="variables_get" id="0Od]fgl3[5@N_7QNzu8H">
                <field name="VAR" id="i:Z4!f)D|*s,oET(5.yJ" variabletype="">logika</field>
              </block>
            </value>
            <value name="B">
              <block type="math_number" id="$WfLK{I[I$97Y1/*(ebW">
                <field name="NUM">1</field>
              </block>
            </value>
          </block>
        </value>
        <statement name="DO0">
          <block type="controls_if" id="_;!rj1L8.=bpg_9D{Rt{">
            <value name="IF0">
              <block type="logic_compare" id="CA8=`CIO7+r_ix83{.m?">
                <field name="OP">EQ</field>
                <value name="A">
                  <block type="variables_get" id="RF+S6=8c3^@[J4h?U5u-">
                    <field name="VAR" id="(5l7?QBe%F}9JdwBk^!e" variabletype="">ekse</field>
                  </block>
                </value>
                <value name="B">
                  <block type="math_number" id="h4d5b{^{?,U^zT*Zb90v">
                    <field name="NUM">1</field>
                  </block>
                </value>
              </block>
            </value>
            <statement name="DO0">
              <block type="controls_if" id="H1Xl-%hm.P(B[3@`ny$D">
                <mutation elseif="1"></mutation>
                <value name="IF0">
                  <block type="logic_compare" id="b/TPiOX=m*u0QmVAQNB/">
                    <field name="OP">EQ</field>
                    <value name="A">
                      <block type="variables_get" id="!K*7eGWzu?v%hr|3Q|s=">
                        <field name="VAR" id="o/=0QCkDSD0FNOZ4LUcH" variabletype="">posisi</field>
                      </block>
                    </value>
                    <value name="B">
                      <block type="math_number" id="y2V!`]*~;:n[AJ=Os#;/">
                        <field name="NUM">2</field>
                      </block>
                    </value>
                  </block>
                </value>
                <statement name="DO0">
                  <block type="controls_if" id="Qb=,Qq:Nt[]:@;~R.4K9">
                    <value name="IF0">
                      <block type="check_sell" id="QWE(toX=_L,1X3svfU;5"></block>
                    </value>
                    <statement name="DO0">
                      <block type="controls_if" id="je@Wd5*9M?1u30DZUqhe">
                        <value name="IF0">
                          <block type="logic_compare" id="u}LgbqV.xu77B%9Rvp1T">
                            <field name="OP">LT</field>
                            <value name="A">
                              <block type="read_ohlc" id="A9o;4}XE@ftC7/Em@2Ey">
                                <field name="OHLCFIELD_LIST">open</field>
                                <field name="CANDLEINTERVAL_LIST">default</field>
                                <value name="CANDLEINDEX">
                                  <shadow type="math_number" id="fm1s9a*ial_x~CV*^s.J">
                                    <field name="NUM">1</field>
                                  </shadow>
                                </value>
                              </block>
                            </value>
                            <value name="B">
                              <block type="tick" id="V`h!BOWDQm.8UQjo9xrh"></block>
                            </value>
                          </block>
                        </value>
                        <statement name="DO0">
                          <block type="sell_at_market" id="w!%Iu0095yoT=+Iv{;6a"></block>
                        </statement>
                      </block>
                    </statement>
                  </block>
                </statement>
                <value name="IF1">
                  <block type="logic_compare" id="J)8PK3wRiN`F)yhb7mQL">
                    <field name="OP">EQ</field>
                    <value name="A">
                      <block type="variables_get" id="jA*_haDduYc1WmM7r2Ma">
                        <field name="VAR" id="o/=0QCkDSD0FNOZ4LUcH" variabletype="">posisi</field>
                      </block>
                    </value>
                    <value name="B">
                      <block type="math_number" id="QMHIN|vMN=^|HOk+7o..">
                        <field name="NUM">1</field>
                      </block>
                    </value>
                  </block>
                </value>
                <statement name="DO1">
                  <block type="controls_if" id="$+E.m[/F};y}uQ;Dv}CK">
                    <value name="IF0">
                      <block type="check_sell" id="he^Q5}YpY2WI6qc+z$W8"></block>
                    </value>
                    <statement name="DO0">
                      <block type="controls_if" id="q{F@QYqKC+qAvLd;N8i/">
                        <value name="IF0">
                          <block type="logic_compare" id="XSB(}h*m@pA.hV^dn]`-">
                            <field name="OP">GT</field>
                            <value name="A">
                              <block type="read_ohlc" id="cz7Ua+ma9@yD^+,^2$3k">
                                <field name="OHLCFIELD_LIST">open</field>
                                <field name="CANDLEINTERVAL_LIST">default</field>
                                <value name="CANDLEINDEX">
                                  <shadow type="math_number" id="!9fBL%9~vxlnDry#C+BU">
                                    <field name="NUM">1</field>
                                  </shadow>
                                </value>
                              </block>
                            </value>
                            <value name="B">
                              <block type="tick" id="GkvvLBJn;f$yYD+~,vwL"></block>
                            </value>
                          </block>
                        </value>
                        <statement name="DO0">
                          <block type="sell_at_market" id="ciXVLl,V2Vm[lXSM%kNA"></block>
                        </statement>
                      </block>
                    </statement>
                  </block>
                </statement>
              </block>
            </statement>
          </block>
        </statement>
      </block>
    </statement>
  </block>
</xml>